zenoai/__init__.py
zenoai/experiment_run.py
zenoai/version.py
zenoai/visualize.py
zenoai-0.0.0a0.dist-info/METADATA
zenoai-0.0.0a0.dist-info/WHEEL
zenoai-0.0.0a0.dist-info/licenses/LICENSE
zenoai-0.0.0a0.dist-info/RECORD
