Metadata-Version: 2.1
Name: zenoai
Version: 0.0.0a0
Summary: Python client for Zeno.
Author-email: Graham Neubig <neubig@gmail.com>
License: MIT License
License-File: LICENSE
Classifier: Programming Language :: Python :: 3.9
Classifier: Programming Language :: Python :: 3.10
Classifier: Programming Language :: Python :: 3.11
Requires-Python: >=3.9
Requires-Dist: zenoml>=0.6.1
Provides-Extra: test
Requires-Dist: black>=23.3.0; extra == 'test'
Requires-Dist: mypy>=1.2.0; extra == 'test'
Requires-Dist: pre-commit>=3.2.0; extra == 'test'
Requires-Dist: pytest>=6.0.0; extra == 'test'
